scripts
tests
ugo
