Metadata-Version: 1.1
Name: ugo
Version: 0.0.3
Summary: ugo base project.
Home-page: https://github.com/showdom/ugo
Author: Showdom
Author-email: 1063951161@qq.com
License: MIT License
Keywords: ugo,tustack
Platform: all
Classifier: Intended Audience :: Developers
Classifier: Topic :: Software Development :: Libraries
Classifier: License :: OSI Approved :: MIT License
Classifier: Programming Language :: Python :: 3
Classifier: Programming Language :: Python :: 3.4
Classifier: Programming Language :: Python :: 3.5
Classifier: Programming Language :: Python :: 3.6
